{
  "task": 348,
  "rerun_for": 349,
  "status": "pass",
  "change_summary": [
    "fallback fixture config is now tenant-scoped",
    "default/northwind-sandbox use only Northwind fixture entity/link sets",
    "creditcardfraud uses only credit_card_transactions_safe fraud fixture entity/link sets",
    "non-demo tenants return no fallback graph when no approved SchemaGraphModelingAgent projection exists"
  ],
  "creditcardfraud": {
    "graph_context": {
      "approved": false,
      "nodes": 0,
      "edges": 0,
      "missing_approved_artifacts": [
        "object:credit_card_transaction",
        "object:account",
        "object:card",
        "object:merchant"
      ],
      "forbidden_artifacts_absent": [
        "object:employee",
        "object:order",
        "object:customer"
      ]
    },
    "types_include_draft": [
      "CreditCardTransaction",
      "Account",
      "Card",
      "Merchant"
    ],
    "employee_search": {
      "instances": 0,
      "reason": "Type Employee is not available in tenant-scoped fallback projection for creditcardfraud"
    }
  },
  "default": {
    "projection_source": "fallback_fixture",
    "contains_northwind_demo": true
  },
  "maritime_risk": {
    "projection_source": "SchemaGraphModelingAgent",
    "center": "Country:CHN"
  },
  "validation": [
    ".venv/bin/python -m py_compile server/workbench_server.py tests/test_continuous_enrichment_frontier.py",
    ".venv/bin/python -m unittest tests/test_continuous_enrichment_frontier.py tests/test_reasoning_deep_graph.py tests/test_schema_graph_modeling_agent.py tests/test_ontology_eval.py tests/test_iterative_graph_enrichment.py",
    "node --check web/app/api.js",
    "npx esbuild web/app/graph.jsx --bundle --format=iife --global-name=GraphApp --outfile=/tmp/aletheia-graph-check.js",
    "git diff --check"
  ],
  "unrelated_dirty_files": [
    "agents/iterative_graph_enrichment_agent.py",
    "tests/test_iterative_graph_enrichment.py"
  ]
}
